{"nodes": [{"id": "c_users_joelt_project_app_features_sectors_services_sectorservice_php", "label": "SectorService.php", "file_type": "code", "source_file": "C:\\Users\\joelt\\project\\app\\Features\\Sectors\\Services\\SectorService.php", "source_location": "L1"}, {"id": "services_sectorservice_sectorservice", "label": "SectorService", "file_type": "code", "source_file": "C:\\Users\\joelt\\project\\app\\Features\\Sectors\\Services\\SectorService.php", "source_location": "L8"}, {"id": "services_sectorservice_sectorservice_construct", "label": ".__construct()", "file_type": "code", "source_file": "C:\\Users\\joelt\\project\\app\\Features\\Sectors\\Services\\SectorService.php", "source_location": "L10"}, {"id": "services_sectorservice_sectorservice_create", "label": ".create()", "file_type": "code", "source_file": "C:\\Users\\joelt\\project\\app\\Features\\Sectors\\Services\\SectorService.php", "source_location": "L14"}, {"id": "services_sectorservice_sectorservice_update", "label": ".update()", "file_type": "code", "source_file": "C:\\Users\\joelt\\project\\app\\Features\\Sectors\\Services\\SectorService.php", "source_location": "L24"}, {"id": "services_sectorservice_sectorservice_delete", "label": ".delete()", "file_type": "code", "source_file": "C:\\Users\\joelt\\project\\app\\Features\\Sectors\\Services\\SectorService.php", "source_location": "L32"}], "edges": [{"source": "c_users_joelt_project_app_features_sectors_services_sectorservice_php", "target": "transactionhandler", "relation": "imports", "context": "import", "confidence": "EXTRACTED", "source_file": "C:\\Users\\joelt\\project\\app\\Features\\Sectors\\Services\\SectorService.php", "source_location": "L5", "weight": 1.0}, {"source": "c_users_joelt_project_app_features_sectors_services_sectorservice_php", "target": "sector", "relation": "imports", "context": "import", "confidence": "EXTRACTED", "source_file": "C:\\Users\\joelt\\project\\app\\Features\\Sectors\\Services\\SectorService.php", "source_location": "L6", "weight": 1.0}, {"source": "c_users_joelt_project_app_features_sectors_services_sectorservice_php", "target": "services_sectorservice_sectorservice", "relation": "contains", "confidence": "EXTRACTED", "source_file": "C:\\Users\\joelt\\project\\app\\Features\\Sectors\\Services\\SectorService.php", "source_location": "L8", "weight": 1.0}, {"source": "services_sectorservice_sectorservice", "target": "services_sectorservice_sectorservice_construct", "relation": "method", "confidence": "EXTRACTED", "source_file": "C:\\Users\\joelt\\project\\app\\Features\\Sectors\\Services\\SectorService.php", "source_location": "L10", "weight": 1.0}, {"source": "services_sectorservice_sectorservice", "target": "services_sectorservice_sectorservice_create", "relation": "method", "confidence": "EXTRACTED", "source_file": "C:\\Users\\joelt\\project\\app\\Features\\Sectors\\Services\\SectorService.php", "source_location": "L14", "weight": 1.0}, {"source": "services_sectorservice_sectorservice", "target": "services_sectorservice_sectorservice_update", "relation": "method", "confidence": "EXTRACTED", "source_file": "C:\\Users\\joelt\\project\\app\\Features\\Sectors\\Services\\SectorService.php", "source_location": "L24", "weight": 1.0}, {"source": "services_sectorservice_sectorservice", "target": "services_sectorservice_sectorservice_delete", "relation": "method", "confidence": "EXTRACTED", "source_file": "C:\\Users\\joelt\\project\\app\\Features\\Sectors\\Services\\SectorService.php", "source_location": "L32", "weight": 1.0}], "raw_calls": [{"caller_nid": "services_sectorservice_sectorservice_create", "callee": "execute", "is_member_call": true, "source_file": "C:\\Users\\joelt\\project\\app\\Features\\Sectors\\Services\\SectorService.php", "source_location": "L16"}, {"caller_nid": "services_sectorservice_sectorservice_create", "callee": "Sector", "is_member_call": false, "source_file": "C:\\Users\\joelt\\project\\app\\Features\\Sectors\\Services\\SectorService.php", "source_location": "L17"}, {"caller_nid": "services_sectorservice_sectorservice_update", "callee": "execute", "is_member_call": true, "source_file": "C:\\Users\\joelt\\project\\app\\Features\\Sectors\\Services\\SectorService.php", "source_location": "L26"}, {"caller_nid": "services_sectorservice_sectorservice_delete", "callee": "execute", "is_member_call": true, "source_file": "C:\\Users\\joelt\\project\\app\\Features\\Sectors\\Services\\SectorService.php", "source_location": "L34"}]}