{"nodes": [{"id": "c_users_joelt_project_app_features_worklogs_controllers_web_worklogpagecontroller_php", "label": "WorkLogPageController.php", "file_type": "code", "source_file": "C:\\Users\\joelt\\project\\app\\Features\\WorkLogs\\Controllers\\Web\\WorkLogPageController.php", "source_location": "L1"}, {"id": "web_worklogpagecontroller_worklogpagecontroller", "label": "WorkLogPageController", "file_type": "code", "source_file": "C:\\Users\\joelt\\project\\app\\Features\\WorkLogs\\Controllers\\Web\\WorkLogPageController.php", "source_location": "L12"}, {"id": "web_worklogpagecontroller_worklogpagecontroller_index", "label": ".index()", "file_type": "code", "source_file": "C:\\Users\\joelt\\project\\app\\Features\\WorkLogs\\Controllers\\Web\\WorkLogPageController.php", "source_location": "L14"}], "edges": [{"source": "c_users_joelt_project_app_features_worklogs_controllers_web_worklogpagecontroller_php", "target": "worklog", "relation": "imports", "context": "import", "confidence": "EXTRACTED", "source_file": "C:\\Users\\joelt\\project\\app\\Features\\WorkLogs\\Controllers\\Web\\WorkLogPageController.php", "source_location": "L5", "weight": 1.0}, {"source": "c_users_joelt_project_app_features_worklogs_controllers_web_worklogpagecontroller_php", "target": "worklogformschema", "relation": "imports", "context": "import", "confidence": "EXTRACTED", "source_file": "C:\\Users\\joelt\\project\\app\\Features\\WorkLogs\\Controllers\\Web\\WorkLogPageController.php", "source_location": "L6", "weight": 1.0}, {"source": "c_users_joelt_project_app_features_worklogs_controllers_web_worklogpagecontroller_php", "target": "request", "relation": "imports", "context": "import", "confidence": "EXTRACTED", "source_file": "C:\\Users\\joelt\\project\\app\\Features\\WorkLogs\\Controllers\\Web\\WorkLogPageController.php", "source_location": "L7", "weight": 1.0}, {"source": "c_users_joelt_project_app_features_worklogs_controllers_web_worklogpagecontroller_php", "target": "controller", "relation": "imports", "context": "import", "confidence": "EXTRACTED", "source_file": "C:\\Users\\joelt\\project\\app\\Features\\WorkLogs\\Controllers\\Web\\WorkLogPageController.php", "source_location": "L8", "weight": 1.0}, {"source": "c_users_joelt_project_app_features_worklogs_controllers_web_worklogpagecontroller_php", "target": "gate", "relation": "imports", "context": "import", "confidence": "EXTRACTED", "source_file": "C:\\Users\\joelt\\project\\app\\Features\\WorkLogs\\Controllers\\Web\\WorkLogPageController.php", "source_location": "L9", "weight": 1.0}, {"source": "c_users_joelt_project_app_features_worklogs_controllers_web_worklogpagecontroller_php", "target": "inertia", "relation": "imports", "context": "import", "confidence": "EXTRACTED", "source_file": "C:\\Users\\joelt\\project\\app\\Features\\WorkLogs\\Controllers\\Web\\WorkLogPageController.php", "source_location": "L10", "weight": 1.0}, {"source": "c_users_joelt_project_app_features_worklogs_controllers_web_worklogpagecontroller_php", "target": "web_worklogpagecontroller_worklogpagecontroller", "relation": "contains", "confidence": "EXTRACTED", "source_file": "C:\\Users\\joelt\\project\\app\\Features\\WorkLogs\\Controllers\\Web\\WorkLogPageController.php", "source_location": "L12", "weight": 1.0}, {"source": "web_worklogpagecontroller_worklogpagecontroller", "target": "web_worklogpagecontroller_worklogpagecontroller_index", "relation": "method", "confidence": "EXTRACTED", "source_file": "C:\\Users\\joelt\\project\\app\\Features\\WorkLogs\\Controllers\\Web\\WorkLogPageController.php", "source_location": "L14", "weight": 1.0}], "raw_calls": [{"caller_nid": "web_worklogpagecontroller_worklogpagecontroller_index", "callee": "Gate", "is_member_call": false, "source_file": "C:\\Users\\joelt\\project\\app\\Features\\WorkLogs\\Controllers\\Web\\WorkLogPageController.php", "source_location": "L16"}, {"caller_nid": "web_worklogpagecontroller_worklogpagecontroller_index", "callee": "through", "is_member_call": true, "source_file": "C:\\Users\\joelt\\project\\app\\Features\\WorkLogs\\Controllers\\Web\\WorkLogPageController.php", "source_location": "L18"}, {"caller_nid": "web_worklogpagecontroller_worklogpagecontroller_index", "callee": "paginate", "is_member_call": true, "source_file": "C:\\Users\\joelt\\project\\app\\Features\\WorkLogs\\Controllers\\Web\\WorkLogPageController.php", "source_location": "L18"}, {"caller_nid": "web_worklogpagecontroller_worklogpagecontroller_index", "callee": "latest", "is_member_call": true, "source_file": "C:\\Users\\joelt\\project\\app\\Features\\WorkLogs\\Controllers\\Web\\WorkLogPageController.php", "source_location": "L18"}, {"caller_nid": "web_worklogpagecontroller_worklogpagecontroller_index", "callee": "WorkLog", "is_member_call": false, "source_file": "C:\\Users\\joelt\\project\\app\\Features\\WorkLogs\\Controllers\\Web\\WorkLogPageController.php", "source_location": "L18"}, {"caller_nid": "web_worklogpagecontroller_worklogpagecontroller_index", "callee": "format", "is_member_call": true, "source_file": "C:\\Users\\joelt\\project\\app\\Features\\WorkLogs\\Controllers\\Web\\WorkLogPageController.php", "source_location": "L26"}, {"caller_nid": "web_worklogpagecontroller_worklogpagecontroller_index", "callee": "join", "is_member_call": true, "source_file": "C:\\Users\\joelt\\project\\app\\Features\\WorkLogs\\Controllers\\Web\\WorkLogPageController.php", "source_location": "L38"}, {"caller_nid": "web_worklogpagecontroller_worklogpagecontroller_index", "callee": "map", "is_member_call": true, "source_file": "C:\\Users\\joelt\\project\\app\\Features\\WorkLogs\\Controllers\\Web\\WorkLogPageController.php", "source_location": "L38"}, {"caller_nid": "web_worklogpagecontroller_worklogpagecontroller_index", "callee": "map", "is_member_call": true, "source_file": "C:\\Users\\joelt\\project\\app\\Features\\WorkLogs\\Controllers\\Web\\WorkLogPageController.php", "source_location": "L39"}, {"caller_nid": "web_worklogpagecontroller_worklogpagecontroller_index", "callee": "WorkLogFormSchema", "is_member_call": false, "source_file": "C:\\Users\\joelt\\project\\app\\Features\\WorkLogs\\Controllers\\Web\\WorkLogPageController.php", "source_location": "L45"}, {"caller_nid": "web_worklogpagecontroller_worklogpagecontroller_index", "callee": "WorkLogFormSchema", "is_member_call": false, "source_file": "C:\\Users\\joelt\\project\\app\\Features\\WorkLogs\\Controllers\\Web\\WorkLogPageController.php", "source_location": "L46"}, {"caller_nid": "web_worklogpagecontroller_worklogpagecontroller_index", "callee": "Inertia", "is_member_call": false, "source_file": "C:\\Users\\joelt\\project\\app\\Features\\WorkLogs\\Controllers\\Web\\WorkLogPageController.php", "source_location": "L48"}, {"caller_nid": "web_worklogpagecontroller_worklogpagecontroller_index", "callee": "toArray", "is_member_call": true, "source_file": "C:\\Users\\joelt\\project\\app\\Features\\WorkLogs\\Controllers\\Web\\WorkLogPageController.php", "source_location": "L59"}, {"caller_nid": "web_worklogpagecontroller_worklogpagecontroller_index", "callee": "toArray", "is_member_call": true, "source_file": "C:\\Users\\joelt\\project\\app\\Features\\WorkLogs\\Controllers\\Web\\WorkLogPageController.php", "source_location": "L60"}, {"caller_nid": "web_worklogpagecontroller_worklogpagecontroller_index", "callee": "url", "is_member_call": false, "source_file": "C:\\Users\\joelt\\project\\app\\Features\\WorkLogs\\Controllers\\Web\\WorkLogPageController.php", "source_location": "L62"}, {"caller_nid": "web_worklogpagecontroller_worklogpagecontroller_index", "callee": "url", "is_member_call": false, "source_file": "C:\\Users\\joelt\\project\\app\\Features\\WorkLogs\\Controllers\\Web\\WorkLogPageController.php", "source_location": "L63"}, {"caller_nid": "web_worklogpagecontroller_worklogpagecontroller_index", "callee": "url", "is_member_call": false, "source_file": "C:\\Users\\joelt\\project\\app\\Features\\WorkLogs\\Controllers\\Web\\WorkLogPageController.php", "source_location": "L64"}, {"caller_nid": "web_worklogpagecontroller_worklogpagecontroller_index", "callee": "url", "is_member_call": false, "source_file": "C:\\Users\\joelt\\project\\app\\Features\\WorkLogs\\Controllers\\Web\\WorkLogPageController.php", "source_location": "L65"}, {"caller_nid": "web_worklogpagecontroller_worklogpagecontroller_index", "callee": "url", "is_member_call": false, "source_file": "C:\\Users\\joelt\\project\\app\\Features\\WorkLogs\\Controllers\\Web\\WorkLogPageController.php", "source_location": "L66"}]}